lettuceSee/__init__.py
lettuceSee/distance.py
lettuceSee/graph.py
lettuceSee/segment.py
lettuceSee/util.py
lettucesee-0.2.2.dist-info/METADATA
lettucesee-0.2.2.dist-info/WHEEL
lettucesee-0.2.2.dist-info/top_level.txt
lettucesee-0.2.2.dist-info/RECORD
