Metadata-Version: 2.4
Name: lettuceSee
Version: 0.2.2
Summary: A package of image analysis algorithms suited for plants
Home-page: https://github.com/Chizz98/LettuceSee
Author: Chris Dijkstra
Author-email: chris_dijkstra98@hotmail.com
Classifier: Development Status :: 2 - Pre-Alpha
Classifier: Topic :: Scientific/Engineering :: Image Processing
Classifier: Intended Audience :: Science/Research
Requires-Dist: scikit-image
Requires-Dist: scipy
Requires-Dist: numpy
Requires-Dist: networkx
Dynamic: author
Dynamic: author-email
Dynamic: classifier
Dynamic: description
Dynamic: description-content-type
Dynamic: home-page
Dynamic: requires-dist
Dynamic: summary
